LICENSE
LICENSE.txt
README.rst
setup.cfg
setup.py
pyxstitch/__init__.py
pyxstitch/character.py
pyxstitch/config.py
pyxstitch/floss.py
pyxstitch/font.py
pyxstitch/formatter.py
pyxstitch/formatter_layout.py
pyxstitch/hex.py
pyxstitch/log.py
pyxstitch/output.py
pyxstitch/pyxstitch.py
pyxstitch/symbols.py
pyxstitch/version.py
pyxstitch.egg-info/PKG-INFO
pyxstitch.egg-info/SOURCES.txt
pyxstitch.egg-info/dependency_links.txt
pyxstitch.egg-info/entry_points.txt
pyxstitch.egg-info/requires.txt
pyxstitch.egg-info/top_level.txt
pyxstitch/fonts/__init__.py
pyxstitch/fonts/five_by_nine_mono.py
pyxstitch/fonts/five_by_nine_prop.py
pyxstitch/fonts/four_by_seven_prop.py
pyxstitch/fonts/three_by_five_mono.py
pyxstitch/fonts/three_by_seven_mono.py
pyxstitch/fonts/three_by_six_prop.py
pyxstitch/fonts/two_by_five_mono.py