Metadata-Version: 2.1
Name: pyxstitch
Version: 1.11.1
Summary: Convert source code to cross stitch patterns
Home-page: https://github.com/enckse/pyxstitch
Author: Sean Enck
Author-email: enckse@voidedtech.com
License: GPL3
Keywords: crossstitch cross stitch
Platform: UNKNOWN
Requires-Python: >=3.7
License-File: LICENSE
License-File: LICENSE.txt
